open_weather_forecast/global_settings.py
open_weather_forecast/logger.py
open_weather_forecast/main.py
open_weather_forecast/get_temperature.py
open_weather_forecast/constants.py
open_weather_forecast/get_info.py
open_weather_forecast/db_connection.py
open_weather_forecast/__init__.py
open_weather_forecast/get_info_abstract.py
open_weather_forecast/http_decorator.py
open_weather_forecast/info_extractor/get_temperature.py
open_weather_forecast/info_extractor/get_info.py
open_weather_forecast/info_extractor/__init__.py
open_weather_forecast/info_extractor/get_info_abstract.py
open_weather_forecast/info_extractor/http_decorator.py
open_weather_forecast/info_extractor/tests/get_info_tests.py
open_weather_forecast/info_extractor/tests/__init__.py
open_weather_forecast/info_extractor/tests/get_temperature_tests.py
open_weather_forecast/info_extractor/tests/http_decorator_tests.py
open_weather_forecast/info_extractor/forecast/get_forecast.py
open_weather_forecast/info_extractor/forecast/__init__.py
open_weather_forecast/info_extractor/forecast/forecast_weather_info.py
open_weather_forecast/info_extractor/temperature/get_temperature.py
open_weather_forecast/info_extractor/temperature/__init__.py
open_weather_forecast/info_extractor/temperature/weather_info.py
open_weather_forecast/tests/get_temperature.py
open_weather_forecast/tests/get_info_tests.py
open_weather_forecast/tests/retry_tests.py
open_weather_forecast/tests/__init__.py
open_weather_forecast/tests/get_temperature_tests.py
open_weather_forecast/tests/http_decorator_tests.py
open_weather_forecast/weather_db/__init__.py
open_weather_forecast/weather_db/forecast_weather_info.py
open_weather_forecast/weather_db/weather_info.py
open_weather_forecast/conf/global_settings.py
open_weather_forecast/conf/logger.py
open_weather_forecast/conf/constants.py
open_weather_forecast/conf/__init__.py
OpenWeatherForecast-0.2.3.dist-info/RECORD
OpenWeatherForecast-0.2.3.dist-info/WHEEL
OpenWeatherForecast-0.2.3.dist-info/DESCRIPTION.rst
OpenWeatherForecast-0.2.3.dist-info/metadata.json
OpenWeatherForecast-0.2.3.dist-info/top_level.txt
OpenWeatherForecast-0.2.3.dist-info/pbr.json
OpenWeatherForecast-0.2.3.dist-info/METADATA
temperature_data/main.py
temperature_data/__init__.py
